garb/FilterLogicalOperator.py
garb/__init__.py
garb/cohort.py
garb/daterange.py
garb/dimension.py
garb/metric.py
garb/order.py
garb/pivot.py
garb/reportRequest.py
garb/segment.py
garb-0.3.0.dist-info/LICENSE.md
garb-0.3.0.dist-info/METADATA
garb-0.3.0.dist-info/WHEEL
garb-0.3.0.dist-info/top_level.txt
garb-0.3.0.dist-info/RECORD
